magtomo/Experiment.py
magtomo/Reconstruction.py
magtomo/__init__.py
magtomo/examples.py
magtomo/radon.py
magtomo-0.1.1.dist-info/licenses/LICENSE.txt
magtomo-0.1.1.dist-info/METADATA
magtomo-0.1.1.dist-info/WHEEL
magtomo-0.1.1.dist-info/top_level.txt
magtomo-0.1.1.dist-info/RECORD
